{
  "media": [
    
  ],
  "label_values": [
    {
      "label": "Name",
      "vec": [
        {
          "value": "Birthday in November"
        },
        {
          "value": "Early technology adopters"
        },
        {
          "value": "Engaged shoppers"
        },
        {
          "value": "Facebook Page admins"
        },
        {
          "value": "Facebook access (browser): Chrome"
        },
        {
          "value": "Facebook access (mobile): Android devices"
        },
        {
          "value": "Facebook access (mobile): Apple (iOS) devices"
        },
        {
          "value": "Facebook access (mobile): all mobile devices"
        },
        {
          "value": "Facebook access (mobile): smartphones and tablets"
        },
        {
          "value": "Facebook access (mobile): tablets"
        },
        {
          "value": "Facebook access (network type): 4G"
        },
        {
          "value": "Frequent travellers"
        },
        {
          "value": "Friends of football fans"
        },
        {
          "value": "Friends of those who live abroad"
        },
        {
          "value": "Large business-to-business enterprise employees (500+ employees)"
        },
        {
          "value": "Mobile network or device users"
        },
        {
          "value": "New Page admins"
        },
        {
          "value": "Parents (All)"
        },
        {
          "value": "Potential mobile network or device change"
        },
        {
          "value": "Recent mobile network or device change"
        },
        {
          "value": "Small business-to-business enterprise employees (10-200 employees)"
        },
        {
          "value": "Uses a mobile device (25 months+)"
        },
        {
          "value": "Wi-Fi Usage"
        }
      ]
    }
  ],
  "fbid": "17841462593825484"
}